huaweicloudsdkdevstar/__init__.py
huaweicloudsdkdevstar/v1/__init__.py
huaweicloudsdkdevstar/v1/devstar_async_client.py
huaweicloudsdkdevstar/v1/devstar_client.py
huaweicloudsdkdevstar/v1/model/__init__.py
huaweicloudsdkdevstar/v1/model/application_base_v3.py
huaweicloudsdkdevstar/v1/model/application_modify_info.py
huaweicloudsdkdevstar/v1/model/application_v3.py
huaweicloudsdkdevstar/v1/model/cci_deployment_jobs_param.py
huaweicloudsdkdevstar/v1/model/check_repository_duplicate_name_request.py
huaweicloudsdkdevstar/v1/model/check_repository_duplicate_name_response.py
huaweicloudsdkdevstar/v1/model/codehub_job_info.py
huaweicloudsdkdevstar/v1/model/confirm_deployment_job_request.py
huaweicloudsdkdevstar/v1/model/confirm_deployment_job_response.py
huaweicloudsdkdevstar/v1/model/create_deployment_jobs_params.py
huaweicloudsdkdevstar/v1/model/create_deployment_jobs_request.py
huaweicloudsdkdevstar/v1/model/create_deployment_jobs_response.py
huaweicloudsdkdevstar/v1/model/create_template_view_histories_request.py
huaweicloudsdkdevstar/v1/model/create_template_view_histories_response.py
huaweicloudsdkdevstar/v1/model/delete_application_v4_request.py
huaweicloudsdkdevstar/v1/model/delete_application_v4_response.py
huaweicloudsdkdevstar/v1/model/dependent.py
huaweicloudsdkdevstar/v1/model/deployment_job_confirm_type.py
huaweicloudsdkdevstar/v1/model/download_application_code_request.py
huaweicloudsdkdevstar/v1/model/download_application_code_response.py
huaweicloudsdkdevstar/v1/model/fgs_deployment_jobs_param.py
huaweicloudsdkdevstar/v1/model/file_tree_node.py
huaweicloudsdkdevstar/v1/model/list_applications_v6_request.py
huaweicloudsdkdevstar/v1/model/list_applications_v6_response.py
huaweicloudsdkdevstar/v1/model/list_pipeline_templates_request.py
huaweicloudsdkdevstar/v1/model/list_pipeline_templates_response.py
huaweicloudsdkdevstar/v1/model/list_projects_v4_request.py
huaweicloudsdkdevstar/v1/model/list_projects_v4_response.py
huaweicloudsdkdevstar-3.1.184.dist-info/METADATA
huaweicloudsdkdevstar-3.1.184.dist-info/WHEEL
huaweicloudsdkdevstar-3.1.184.dist-info/licenses/LICENSE
huaweicloudsdkdevstar-3.1.184.dist-info/RECORD
